sigma/backends/loki/__init__.py
sigma/backends/loki/deferred.py
sigma/backends/loki/loki.py
sigma/pipelines/loki/__init__.py
sigma/pipelines/loki/loki.py
sigma/shared.py
pysigma_backend_loki-0.12.4.dist-info/LICENSE
pysigma_backend_loki-0.12.4.dist-info/METADATA
pysigma_backend_loki-0.12.4.dist-info/WHEEL
pysigma_backend_loki-0.12.4.dist-info/RECORD
