Metadata-Version: 2.1
Name: pySigma-backend-loki
Version: 0.12.4
Summary: pySigma Loki backend
Home-page: https://github.com/grafana/pySigma-backend-loki
License: AGPL-3.0-only
Author: Nick Moore
Author-email: nicholas.moore@grafana.com
Requires-Python: >=3.9,<4.0
Classifier: License :: OSI Approved :: GNU Affero General Public License v3
Classifier: Programming Language :: Python :: 3
Classifier: Programming Language :: Python :: 3.9
Classifier: Programming Language :: Python :: 3.10
Classifier: Programming Language :: Python :: 3.11
Classifier: Programming Language :: Python :: 3.12
Requires-Dist: pysigma (>=0.11.22,<0.12.0)
Project-URL: Repository, https://github.com/grafana/pySigma-backend-loki
